AUTHORS.rst
CONTRIBUTING.rst
HISTORY.rst
LICENSE
MANIFEST.in
README
README.rst
setup.py
yadi/__init__.py
yadi/yadi.py
yadi.egg-info/PKG-INFO
yadi.egg-info/SOURCES.txt
yadi.egg-info/dependency_links.txt
yadi.egg-info/not-zip-safe
yadi.egg-info/requires.txt
yadi.egg-info/top_level.txt
yadi/datalog2sql/__init__.py
yadi/datalog2sql/datalog2sqlconverter.py
yadi/datalog2sql/ast2sql/__init__.py
yadi/datalog2sql/ast2sql/ast2sqlconverter.py
yadi/datalog2sql/ast2sql/exceptions.py
yadi/datalog2sql/ast2sql/preprocessor.py
yadi/datalog2sql/ast2sql/safety_checker.py
yadi/datalog2sql/ast2sql/sql_generator.py
yadi/datalog2sql/parse2tokens/__init__.py
yadi/datalog2sql/parse2tokens/parser.py
yadi/datalog2sql/parse2tokens/parser_tests.py
yadi/datalog2sql/query_data_structures/__init__.py
yadi/datalog2sql/query_data_structures/constraint.py
yadi/datalog2sql/query_data_structures/element.py
yadi/datalog2sql/query_data_structures/query.py
yadi/datalog2sql/query_data_structures/relation.py
yadi/datalog2sql/tokens2ast/__init__.py
yadi/datalog2sql/tokens2ast/ast_builder.py
yadi/datalog2sql/tokens2ast/ast_builder_tester.py
yadi/datalog2sql/tokens2ast/rule_handler.py
yadi/interpreter/__init__.py
yadi/interpreter/interpreter_parse.py
yadi/interpreter/syntax_highlighter.py
yadi/sql_engine/__init__.py
yadi/sql_engine/db_state_tracker.py
yadi/sql_engine/query_evaluator.py